FootballStats/__init__.py
FootballStats/data_setup.py
FootballStats/data/fbref_player_ids.json
FootballStats/data/fbref_team_ids.json
FootballStats/data/fifa_player_ids.json
FootballStats/data/fifa_versions.json
FootballStats/data/historical_odds.csv
FootballStats/objects/__init__.py
FootballStats/objects/constants.py
FootballStats/objects/fifa_data.py
FootballStats/objects/ref_objects.py
FootballStats/odds/get_odds.py
FootballStats/odds/odds_strategies.py
FootballStats/scraping/__init__.py
FootballStats/scraping/common.py
FootballStats/scraping/fbref.py
FootballStats/scraping/fifa_index.py
football_statistics-0.0.7.dist-info/METADATA
football_statistics-0.0.7.dist-info/WHEEL
football_statistics-0.0.7.dist-info/top_level.txt
football_statistics-0.0.7.dist-info/RECORD
