Metadata-Version: 2.1
Name: football-statistics
Version: 0.0.7
Summary: Package for centralized football statistics
Home-page: https://github.com/maxhleonard/football
Author: Max Leonard
Author-email: maxhleonard@gmail.com
License: UNKNOWN
Project-URL: Bug Tracker, https://github.com/pypa/sampleproject/issues
Platform: UNKNOWN
Classifier: Programming Language :: Python :: 3
Classifier: License :: OSI Approved :: MIT License
Classifier: Operating System :: OS Independent
Requires-Python: >=3.6
Requires-Dist: pandas
Requires-Dist: beautifulsoup4
